{
  "variants": {
    "type=bottom,facing=south": {
      "model": "minecraft:block/cobblestone_stairs",
      "y": 90,
      "uvlock": true
    },
    "type=bottom,facing=west": {
      "model": "minecraft:block/cobblestone_stairs",
      "y": 180,
      "uvlock": true
    },
    "type=bottom,facing=north": {
      "model": "minecraft:block/cobblestone_stairs",
      "y": 270,
      "uvlock": true
    },
    "type=bottom,facing=east": {
      "model": "minecraft:block/cobblestone_stairs",
      "uvlock": true
    },
    "type=top,facing=south": {
      "model": "minecraft:block/cobblestone_stairs",
      "x": 270,
      "y": 90,
      "uvlock": true
    },
    "type=top,facing=west": {
      "model": "minecraft:block/cobblestone_stairs",
      "x": 270,
      "y": 180,
      "uvlock": true
    },
    "type=top,facing=north": {
      "model": "minecraft:block/cobblestone_stairs",
      "x": 270,
      "y": 270,
      "uvlock": true
    },
    "type=top,facing=east": {
      "model": "minecraft:block/cobblestone_stairs",
      "x": 270,
      "uvlock": true
    }
  }
}
